funiest/__init__.py
funiest/will_test.py
funiest-0.0.1.dist-info/DESCRIPTION.rst
funiest-0.0.1.dist-info/METADATA
funiest-0.0.1.dist-info/RECORD
funiest-0.0.1.dist-info/WHEEL
funiest-0.0.1.dist-info/metadata.json
funiest-0.0.1.dist-info/top_level.txt
