Metadata-Version: 2.0
Name: funiest
Version: 0.0.1
Summary: The funniest joke in the world
Home-page: http://github.com/willcup/funiest
Author: Flying Circus
Author-email: flyingcircus@example.com
License: MIT
Platform: UNKNOWN
